{
    "id": "7ed2fe70-6312-44f7-bd53-5edd178a8741",
    "type": "Screen",
    "translatedName": "Screen",
    "reactType": "ViewWithProps",
    "properties": {
        "Height": "Fill container",
        "Width": "Fill container",
        "Layout": "column",
        "Justification": "center",
        "Alignment": "center",
        "Visible": true,
        "style": {
            "marginTop": 0,
            "marginBottom": 0,
            "marginLeft": 0,
            "marginRight": 0,
            "paddingTop": 0,
            "paddingBottom": 0,
            "paddingLeft": 0,
            "paddingRight": 0,
            "shadowColor": "rgba(0, 0, 0, 0)",
            "shadowOpacity": 0,
            "scaledShadowOpacity": 0,
            "shadowRadius": 0,
            "shadowOffset": {
                "width": 0,
                "height": 0
            },
            "flexDirection": "column",
            "justifyContent": "center",
            "alignItems": "center",
            "display": "flex",
            "backgroundColor": "rgba(23, 240, 36, 1)"
        },
        "ShowStatusBar": true,
        "StatusBarStyle": "default",
        "TranslucentStatusBar": false,
        "StatusBarColor": "rgba(0,0,0,0.53)",
        "TabNavigationOptions": {
            "tabBarVisible": true
        },
        "TabNavigatorIcon": {},
        "DrawerNavigationOptions": {},
        "StackNavigationOptions": {
            "headerStyle": {}
        },
        "ScreenOrientation": "portrait",
        "DesignerHeight": 667,
        "DesignerWidth": 375,
        "ResponsiveWidth": 375,
        "isSimple": true,
        "navigationOptions": {
            "headerStyle": {}
        },
        "tabNavigationOptions": {},
        "BackgroundColor": "rgba(23, 240, 36, 1)"
    },
    "children": [
        {
            "type": "Button",
            "translatedName": "Button",
            "properties": {
                "Text": "To Video Screen",
                "TextColor": "#FFFFFF",
                "FontSize": 16,
                "Font": "",
                "CustomFont": "",
                "BackgroundColor": "rgba(0, 0, 0, 1)",
                "Height": 79,
                "Width": 82,
                "Visible": true,
                "X": 281,
                "Y": 459,
                "RelativeX": 281,
                "RelativeY": 459,
                "ResizeMode": "STRETCH",
                "style": {
                    "marginTop": 0,
                    "marginBottom": 0,
                    "marginLeft": 0,
                    "marginRight": 0,
                    "paddingTop": 0,
                    "paddingBottom": 0,
                    "paddingLeft": 0,
                    "paddingRight": 0,
                    "borderRadius": 15,
                    "shadowColor": "rgba(0, 0, 0, 0)",
                    "shadowOpacity": 0,
                    "scaledShadowOpacity": 0,
                    "shadowRadius": 0,
                    "shadowOffset": {
                        "width": 0,
                        "height": 0
                    },
                    "position": "absolute",
                    "left": "60.666666666666664%",
                    "top": "82.24793853073463%",
                    "display": "flex"
                },
                "FontBold": false,
                "FontItalic": false,
                "Raised": false,
                "Disabled": false,
                "ParentId": "7ed2fe70-6312-44f7-bd53-5edd178a8741",
                "position": "absolute",
                "edgeOffsets": 459
            },
            "children": [],
            "id": "e62504de-6656-4d75-a38f-9d99e5b8c3b4",
            "thunkableVersion": 443,
            "name": "toVidScreenButton"
        },
        {
            "type": "Image",
            "translatedName": "Image",
            "properties": {
                "Picture": "305soft-high-resolution-color-logo.png",
                "resizeMode": "stretch",
                "Height": 118,
                "Width": 154,
                "Visible": true,
                "X": 110,
                "Y": 439,
                "RelativeX": 110,
                "RelativeY": 439,
                "ResizeMode": "STRETCH",
                "style": {
                    "marginTop": 0,
                    "marginBottom": 0,
                    "marginLeft": 0,
                    "marginRight": 0,
                    "paddingTop": 0,
                    "paddingBottom": 0,
                    "paddingLeft": 0,
                    "paddingRight": 0,
                    "shadowColor": "rgba(0, 0, 0, 0)",
                    "shadowOpacity": 0,
                    "scaledShadowOpacity": 0,
                    "shadowRadius": 0,
                    "shadowOffset": {
                        "width": 0,
                        "height": 0
                    },
                    "position": "absolute",
                    "left": "28.933333333333334%",
                    "top": "65.90610944527737%",
                    "display": "flex"
                },
                "capInsets": {},
                "ParentId": "7ed2fe70-6312-44f7-bd53-5edd178a8741",
                "position": "absolute",
                "edgeOffsets": 439
            },
            "children": [],
            "id": "998f6ac7-4dea-493e-b919-dddb9fb846e1",
            "thunkableVersion": 443,
            "name": "logo"
        },
        {
            "type": "Label",
            "translatedName": "Label",
            "reactType": "Text",
            "properties": {
                "Text": "Dante's Camera App",
                "FontSize": 18,
                "Font": "Merriweather",
                "CustomFont": "",
                "LineHeight": 1,
                "Color": "rgba(202, 37, 37, 1)",
                "BackgroundColor": "rgba(35, 35, 35, 1)",
                "Height": 30,
                "Width": 186,
                "Visible": true,
                "X": 85,
                "Y": 7,
                "RelativeX": 85,
                "RelativeY": 7,
                "ResizeMode": "STRETCH",
                "style": {
                    "color": "rgba(202, 37, 37, 1)",
                    "fontSize": 18,
                    "fontStyle": "normal",
                    "textShadowOffset": {},
                    "letterSpacing": 0,
                    "textDecorationLine": "none",
                    "textDecorationStyle": "solid",
                    "textDecorationColor": "rgba(0, 0, 0, 1)",
                    "writingDirection": "auto",
                    "marginTop": 0,
                    "marginBottom": 0,
                    "marginLeft": 0,
                    "marginRight": 0,
                    "paddingTop": 0,
                    "paddingBottom": 0,
                    "paddingLeft": 0,
                    "paddingRight": 0,
                    "flexWrap": "wrap",
                    "borderWidth": 0,
                    "borderRadius": 0,
                    "borderColor": "rgba(236, 237, 237, 1)",
                    "borderStyle": "dashed",
                    "shadowColor": "rgba(0, 0, 0, 0)",
                    "shadowOpacity": 0,
                    "scaledShadowOpacity": 0,
                    "shadowRadius": 0,
                    "shadowOffset": {
                        "width": 0,
                        "height": 0
                    },
                    "position": "absolute",
                    "left": "28.933333333333334%",
                    "top": "67.85513493253373%",
                    "lineHeight": 1,
                    "display": "flex",
                    "backgroundColor": "rgba(35, 35, 35, 1)"
                },
                "ParentId": "7ed2fe70-6312-44f7-bd53-5edd178a8741",
                "position": "absolute",
                "edgeOffsets": 7.999999999999998,
                "children": "Dante's Camera App"
            },
            "children": [],
            "id": "22a5f882-599f-40b0-b412-d19c0bed469f",
            "thunkableVersion": 443,
            "name": "Name"
        },
        {
            "type": "Button",
            "translatedName": "Button",
            "properties": {
                "Text": "Upload to Cloud",
                "TextColor": "#FFFFFF",
                "FontSize": 16,
                "Font": "",
                "CustomFont": "",
                "BackgroundColor": "rgba(15, 54, 229, 1)",
                "Height": 49,
                "Width": 311,
                "Visible": true,
                "X": 32,
                "Y": 391,
                "RelativeX": 32,
                "RelativeY": 391,
                "ResizeMode": "STRETCH",
                "style": {
                    "marginTop": 0,
                    "marginBottom": 0,
                    "marginLeft": 0,
                    "marginRight": 0,
                    "paddingTop": 0,
                    "paddingBottom": 0,
                    "paddingLeft": 0,
                    "paddingRight": 0,
                    "borderRadius": 15,
                    "shadowColor": "rgba(0, 0, 0, 0)",
                    "shadowOpacity": 0,
                    "scaledShadowOpacity": 0,
                    "shadowRadius": 0,
                    "shadowOffset": {
                        "width": 0,
                        "height": 0
                    },
                    "position": "absolute",
                    "left": "23.066666666666666%",
                    "top": "60.11994002998501%",
                    "display": "flex"
                },
                "FontBold": false,
                "FontItalic": false,
                "Raised": false,
                "Disabled": false,
                "ParentId": "7ed2fe70-6312-44f7-bd53-5edd178a8741",
                "position": "absolute",
                "edgeOffsets": 391
            },
            "children": [],
            "id": "83324ac8-54ac-4dc8-9df8-d6c9f55796e1",
            "thunkableVersion": 443,
            "name": "CloudButton"
        },
        {
            "type": "Button",
            "translatedName": "Button",
            "properties": {
                "Text": "Scan QR Code",
                "TextColor": "#FFFFFF",
                "FontSize": 16,
                "Font": "",
                "CustomFont": "",
                "BackgroundColor": "rgba(228, 93, 252, 1)",
                "Height": 67,
                "Width": 87,
                "Visible": true,
                "X": 264,
                "Y": 298,
                "RelativeX": 264,
                "RelativeY": 298,
                "ResizeMode": "STRETCH",
                "style": {
                    "marginTop": 0,
                    "marginBottom": 0,
                    "marginLeft": 0,
                    "marginRight": 0,
                    "paddingTop": 0,
                    "paddingBottom": 0,
                    "paddingLeft": 0,
                    "paddingRight": 0,
                    "borderRadius": 15,
                    "shadowColor": "rgba(0, 0, 0, 0)",
                    "shadowOpacity": 0,
                    "scaledShadowOpacity": 0,
                    "shadowRadius": 0,
                    "shadowOffset": {
                        "width": 0,
                        "height": 0
                    },
                    "position": "absolute",
                    "left": "43.333333333333336%",
                    "top": "61.91904047976012%",
                    "display": "flex"
                },
                "FontBold": false,
                "FontItalic": false,
                "Raised": false,
                "Disabled": false,
                "ParentId": "7ed2fe70-6312-44f7-bd53-5edd178a8741",
                "position": "absolute",
                "edgeOffsets": 298
            },
            "children": [],
            "id": "38b22d63-1b53-422c-9fb8-f8d589dcaa75",
            "thunkableVersion": 443,
            "name": "QRButton"
        },
        {
            "type": "Button",
            "translatedName": "Button",
            "properties": {
                "Text": "Describe This Image",
                "TextColor": "#FFFFFF",
                "FontSize": 16,
                "Font": "",
                "CustomFont": "",
                "BackgroundColor": "rgba(0, 0, 0, 1)",
                "Height": 76,
                "Width": 102,
                "Visible": true,
                "X": 147,
                "Y": 294,
                "RelativeX": 147,
                "RelativeY": 294,
                "ResizeMode": "STRETCH",
                "style": {
                    "marginTop": 0,
                    "marginBottom": 0,
                    "marginLeft": 0,
                    "marginRight": 0,
                    "paddingTop": 0,
                    "paddingBottom": 0,
                    "paddingLeft": 0,
                    "paddingRight": 0,
                    "borderRadius": 15,
                    "shadowColor": "rgba(0, 0, 0, 0)",
                    "shadowOpacity": 0,
                    "scaledShadowOpacity": 0,
                    "shadowRadius": 0,
                    "shadowOffset": {
                        "width": 0,
                        "height": 0
                    },
                    "position": "absolute",
                    "left": "13.733333333333333%",
                    "top": "66.86656671664169%",
                    "display": "flex"
                },
                "FontBold": false,
                "FontItalic": false,
                "Raised": false,
                "Disabled": false,
                "ParentId": "7ed2fe70-6312-44f7-bd53-5edd178a8741",
                "position": "absolute",
                "edgeOffsets": 294
            },
            "children": [],
            "id": "dfc18e33-f09f-4416-8908-b7d464be26d5",
            "thunkableVersion": 443,
            "name": "DescribeButton"
        },
        {
            "type": "Label",
            "translatedName": "Label",
            "reactType": "Text",
            "properties": {
                "Text": "Label",
                "FontSize": 18,
                "Font": "",
                "CustomFont": "",
                "LineHeight": 1,
                "Color": "rgba(0, 0, 0, 1)",
                "Height": 110,
                "Width": 375,
                "Visible": true,
                "X": 0,
                "Y": 557,
                "RelativeX": 0,
                "RelativeY": 557,
                "ResizeMode": "STRETCH",
                "style": {
                    "color": "rgba(0, 0, 0, 1)",
                    "fontSize": 18,
                    "fontStyle": "normal",
                    "textShadowOffset": {},
                    "letterSpacing": 0,
                    "textDecorationLine": "none",
                    "textDecorationStyle": "solid",
                    "textDecorationColor": "rgba(0, 0, 0, 1)",
                    "writingDirection": "auto",
                    "marginTop": 0,
                    "marginBottom": 0,
                    "marginLeft": 0,
                    "marginRight": 0,
                    "paddingTop": 0,
                    "paddingBottom": 0,
                    "paddingLeft": 0,
                    "paddingRight": 0,
                    "flexWrap": "wrap",
                    "borderWidth": 0,
                    "borderRadius": 0,
                    "borderColor": "rgba(236, 237, 237, 1)",
                    "borderStyle": "solid",
                    "shadowColor": "rgba(0, 0, 0, 0)",
                    "shadowOpacity": 0,
                    "scaledShadowOpacity": 0,
                    "shadowRadius": 0,
                    "shadowOffset": {
                        "width": 0,
                        "height": 0
                    },
                    "position": "absolute",
                    "left": "13.2%",
                    "top": "70.61469265367316%",
                    "lineHeight": 1,
                    "display": "flex"
                },
                "ParentId": "7ed2fe70-6312-44f7-bd53-5edd178a8741",
                "position": "absolute",
                "edgeOffsets": 557,
                "children": "Label"
            },
            "children": [],
            "id": "9ba550c7-ab2d-4b25-acd3-56bca1a59bf4",
            "thunkableVersion": 443,
            "name": "DescriptionLabel"
        },
        {
            "type": "Button",
            "translatedName": "Button",
            "properties": {
                "Text": "Show Image From Photo Library",
                "TextColor": "rgba(216, 17, 17, 1)",
                "FontSize": 16,
                "Font": "",
                "CustomFont": "",
                "BackgroundColor": "rgba(252, 204, 93, 1)",
                "Height": 85,
                "Width": 103,
                "Visible": true,
                "X": 32,
                "Y": 290,
                "RelativeX": 32,
                "RelativeY": 290,
                "ResizeMode": "STRETCH",
                "style": {
                    "marginTop": 0,
                    "marginBottom": 0,
                    "marginLeft": 0,
                    "marginRight": 0,
                    "paddingTop": 0,
                    "paddingBottom": 0,
                    "paddingLeft": 0,
                    "paddingRight": 0,
                    "borderRadius": 15,
                    "shadowColor": "rgba(0, 0, 0, 0)",
                    "shadowOpacity": 0,
                    "scaledShadowOpacity": 0,
                    "shadowRadius": 0,
                    "shadowOffset": {
                        "width": 0,
                        "height": 0
                    },
                    "position": "absolute",
                    "left": "8.4%",
                    "top": "63.392522488755624%",
                    "display": "flex"
                },
                "FontBold": false,
                "FontItalic": false,
                "Raised": false,
                "Disabled": false,
                "ParentId": "7ed2fe70-6312-44f7-bd53-5edd178a8741",
                "position": "absolute",
                "edgeOffsets": 290
            },
            "children": [],
            "id": "37efeb4d-0876-4ed8-88ac-e5c41ab0ace1",
            "thunkableVersion": 443,
            "name": "LibraryButton"
        },
        {
            "type": "Button",
            "translatedName": "Button",
            "properties": {
                "Text": "Show Image From Camera",
                "TextColor": "#FFFFFF",
                "FontSize": 16,
                "Font": "",
                "CustomFont": "",
                "BackgroundColor": "rgba(252, 99, 93, 1)",
                "Height": 49,
                "Width": 311,
                "Visible": true,
                "X": 32,
                "Y": 236,
                "RelativeX": 32,
                "RelativeY": 236,
                "ResizeMode": "STRETCH",
                "style": {
                    "marginTop": 0,
                    "marginBottom": 0,
                    "marginLeft": 0,
                    "marginRight": 0,
                    "paddingTop": 0,
                    "paddingBottom": 0,
                    "paddingLeft": 0,
                    "paddingRight": 0,
                    "borderRadius": 15,
                    "shadowColor": "rgba(0, 0, 0, 0)",
                    "shadowOpacity": 0,
                    "scaledShadowOpacity": 0,
                    "shadowRadius": 0,
                    "shadowOffset": {
                        "width": 0,
                        "height": 0
                    },
                    "position": "absolute",
                    "left": "36.4%",
                    "top": "49.4494940029985%",
                    "display": "flex"
                },
                "FontBold": false,
                "FontItalic": false,
                "Raised": false,
                "Disabled": false,
                "ParentId": "7ed2fe70-6312-44f7-bd53-5edd178a8741",
                "position": "absolute",
                "edgeOffsets": 236
            },
            "children": [],
            "id": "18419b9e-50d8-4700-b211-a55269d2a939",
            "thunkableVersion": 443,
            "name": "CameraButton"
        },
        {
            "type": "Image",
            "translatedName": "Image",
            "properties": {
                "resizeMode": "contain",
                "Height": 196,
                "Width": 379,
                "Visible": true,
                "X": 0,
                "Y": 40,
                "RelativeX": 0,
                "RelativeY": 40,
                "ResizeMode": "STRETCH",
                "style": {
                    "marginTop": 0,
                    "marginBottom": 0,
                    "marginLeft": 0,
                    "marginRight": 0,
                    "paddingTop": 0,
                    "paddingBottom": 0,
                    "paddingLeft": 0,
                    "paddingRight": 0,
                    "shadowColor": "rgba(0, 0, 0, 0)",
                    "shadowOpacity": 0,
                    "scaledShadowOpacity": 0,
                    "shadowRadius": 0,
                    "shadowOffset": {
                        "width": 0,
                        "height": 0
                    },
                    "position": "absolute",
                    "left": "30.266666666666666%",
                    "top": "14.966735382308846%",
                    "display": "flex"
                },
                "capInsets": {},
                "ParentId": "7ed2fe70-6312-44f7-bd53-5edd178a8741",
                "position": "absolute",
                "edgeOffsets": 40
            },
            "children": [],
            "id": "b6df6030-6e0c-46a2-8a67-fa8662fd6061",
            "thunkableVersion": 443,
            "name": "Image1"
        }
    ],
    "thunkableVersion": 443,
    "name": "Photo Screen"
}